django_connexion/__init__.py
django_connexion/apis/__init__.py
django_connexion/apis/django_api.py
django_connexion/apis/django_utils.py
django_connexion/apps/__init__.py
django_connexion/apps/django_app.py
django_connexion/security/__init__.py
django_connexion/security/django_security_handler_factory.py
django_connexion/tests/__init__.py
django_connexion/tests/test_basic.py
django_connexion/tests/testapp/__init__.py
django_connexion/tests/testapp/apis.py
django_connexion/tests/testapp/settings.py
django_connexion/tests/testapp/urls.py
django_connexion/tests/testapp/views.py
django_connexion-0.0.2.dist-info/METADATA
django_connexion-0.0.2.dist-info/WHEEL
django_connexion-0.0.2.dist-info/top_level.txt
django_connexion-0.0.2.dist-info/RECORD
