Metadata-Version: 2.1
Name: django-connexion
Version: 0.0.2
Summary: Django connexion extension
Home-page: https://github.com/buserbrasil/django-connexion
Author: Iuri de Silvio
Author-email: iurisilvio@gmail.com
License: UNKNOWN
Platform: UNKNOWN
Classifier: Development Status :: 3 - Alpha
Classifier: Intended Audience :: Developers
Classifier: Operating System :: OS Independent
Classifier: Framework :: Django
Classifier: Programming Language :: Python :: 3
Classifier: Programming Language :: Python :: 3 :: Only
Classifier: Topic :: Software Development :: Libraries :: Python Modules
Requires-Dist: connexion
Requires-Dist: django
